lab01/src/Sumador.v
module Sumador(
    input A,
    input B,
    input Ci,
    output S,
    output Co
);

assign S = Ci^(A^B);
assign Co = Ci&(A^B)|A&B;


endmodule

lab01/src/sumador_r.v
module sumador_r(
    input  [3:0] A,
    input  [3:0] B,
    input        Ci,
    output [3:0] S,
    output       Co
);

    // =========================================================================
    // CABLES INTERNOS (Como puentes en una protoboard)
    // =========================================================================
    
    // Cables de la Etapa 1
    wire [3:0] cable_B_xor;         // Conecta las compuertas XOR con los primeros sumadores
    wire [3:0] cable_S_intermedio;  // Salida de los primeros sumadores (AÚN NO VA A LOS LEDS)
    wire c1, c2, c3;                // Acarreos entre los primeros sumadores
    wire cable_Co_intermedio;       // El acarreo final de la primera suma
    
    // Cable detector
    wire cable_es_negativo;         // Se enciende (1) solo si estamos restando y el resultado fue negativo
    
    // Cables de la Etapa 2
    wire [3:0] cable_S_invertido;   // Conecta las segundas XOR con los últimos sumadores
    wire k1, k2, k3, k4;            // Acarreos entre los últimos sumadores

    // =========================================================================
    // ETAPA 1: TU SUMADOR/RESTADOR ORIGINAL
    // =========================================================================
    
    assign cable_B_xor[0] = Ci ^ B[0];
    assign cable_B_xor[1] = Ci ^ B[1];
    assign cable_B_xor[2] = Ci ^ B[2];
    assign cable_B_xor[3] = Ci ^ B[3];

    Sumador uno   (.A(A[0]), .B(cable_B_xor[0]), .Ci(Ci), .S(cable_S_intermedio[0]), .Co(c1));
    Sumador dos   (.A(A[1]), .B(cable_B_xor[1]), .Ci(c1), .S(cable_S_intermedio[1]), .Co(c2));
    Sumador tres  (.A(A[2]), .B(cable_B_xor[2]), .Ci(c2), .S(cable_S_intermedio[2]), .Co(c3));
    Sumador cuatro(.A(A[3]), .B(cable_B_xor[3]), .Ci(c3), .S(cable_S_intermedio[3]), .Co(cable_Co_intermedio));

    // El LED de acarreo (Co) va directo al resultado del cuarto sumador. 
    // Como tú dijiste: si es resta y Co está apagado (0), sabes visualmente que es negativo.
    assign Co = cable_Co_intermedio;

    // Detectamos físicamente si es negativo: Selector en 1 (Resta) AND Acarreo apagado (0)
    assign cable_es_negativo = Ci & (~cable_Co_intermedio);

    // =========================================================================
    // ETAPA 2: CORRECCIÓN PARA LOS 4 LEDS DE SALIDA (S)
    // =========================================================================
    
    // Si el 'cable_es_negativo' lleva corriente (1), estas XOR invierten los 4 bits.
    // Si no lleva corriente (0), los dejan pasar igualitos.
    assign cable_S_invertido[0] = cable_S_intermedio[0] ^ cable_es_negativo;
    assign cable_S_invertido[1] = cable_S_intermedio[1] ^ cable_es_negativo;
    assign cable_S_invertido[2] = cable_S_intermedio[2] ^ cable_es_negativo;
    assign cable_S_invertido[3] = cable_S_intermedio[3] ^ cable_es_negativo;

    // Fila final de sumadores. Su única función es sumar un '1' si el número era negativo 
    // (para completar el complemento a 2). 
    // Las salidas de estos sumadores SÍ van conectadas directamente a los pines de tus 4 LEDs de salida (S).
    Sumador cinco (.A(cable_S_invertido[0]), .B(1'b0), .Ci(cable_es_negativo), .S(S[0]), .Co(k1));
    Sumador seis  (.A(cable_S_invertido[1]), .B(1'b0), .Ci(k1),                .S(S[1]), .Co(k2));
    Sumador siete (.A(cable_S_invertido[2]), .B(1'b0), .Ci(k2),                .S(S[2]), .Co(k3));
    Sumador ocho  (.A(cable_S_invertido[3]), .B(1'b0), .Ci(k3),                .S(S[3]), .Co(k4));

endmodule

lab01/src/sumador_r_tb.v
`timescale 1ns/1ps

module sumador_r_tb();

    // =========================================================
    // ENTRADAS (Simulan los interruptores físicos)
    // =========================================================
    reg [3:0] A_tb;
    reg [3:0] B_tb;
    reg       Ci_tb;

    // =========================================================
    // SALIDAS (Simulan los LEDs físicos)
    // =========================================================
    wire [3:0] S_tb;
    wire       Co_tb;

    integer i, j;

    // =========================================================
    // INSTANCIA DEL MÓDULO (Conectar los cables virtuales)
    // =========================================================
    sumador_r lito_r (
        .A(A_tb),
        .B(B_tb),
        .Ci(Ci_tb),
        .S(S_tb),
        .Co(Co_tb)
    );

    // =========================================================
    // GENERACIÓN DE ESTÍMULOS
    // =========================================================
    initial begin
        // Estado inicial (todo apagado)
        A_tb = 4'b0000;
        B_tb = 4'b0000;
        Ci_tb = 1'b0;

        // --- PRUEBA 1: 256 casos de SUMA (Selector Ci = 0) ---
        Ci_tb = 1'b0;
        for (i = 0; i < 16; i = i + 1) begin
            for (j = 0; j < 16; j = j + 1) begin
                A_tb = i;
                B_tb = j;
                #5; // Espera 5 nanosegundos para estabilizar compuertas
            end
        end

        // --- PRUEBA 2: 256 casos de RESTA (Selector Ci = 1) ---
        Ci_tb = 1'b1;
        for (i = 0; i < 16; i = i + 1) begin
            for (j = 0; j < 16; j = j + 1) begin
                A_tb = i;
                B_tb = j;
                #5; // Espera 5 nanosegundos
            end
        end

        $display("Simulacion finalizada correctamente.");
        $finish;
    end

    // =========================================================
    // ARCHIVO PARA GTKWAVE
    // =========================================================
    initial begin
        $dumpfile("build/simulacion_r_tb.vcd");
        $dumpvars(0, sumador_r_tb);
    end

endmodule

lab01/build/simulacion_r_tb.vcd
$date
	Thu Aug 27 19:37:10 2026
$end
$version
	Icarus Verilog
$end
$timescale
	1ps
$end
$scope module sumador_r_tb $end
$var wire 4 ! S_tb [3:0] $end
$var wire 1 " Co_tb $end
$var reg 4 # A_tb [3:0] $end
$var reg 4 $ B_tb [3:0] $end
$var reg 1 % Ci_tb $end
$var integer 32 & i [31:0] $end
$var integer 32 ' j [31:0] $end
$scope module lito_r $end
$var wire 4 ( A [3:0] $end
$var wire 4 ) B [3:0] $end
$var wire 1 % Ci $end
$var wire 1 " Co $end
$var wire 1 * cable_es_negativo $end
$var wire 1 + k4 $end
$var wire 1 , k3 $end
$var wire 1 - k2 $end
$var wire 1 . k1 $end
$var wire 4 / cable_S_invertido [3:0] $end
$var wire 4 0 cable_S_intermedio [3:0] $end
$var wire 1 1 cable_Co_intermedio $end
$var wire 4 2 cable_B_xor [3:0] $end
$var wire 1 3 c3 $end
$var wire 1 4 c2 $end
$var wire 1 5 c1 $end
$var wire 4 6 S [3:0] $end
$scope module cinco $end
$var wire 1 7 A $end
$var wire 1 8 B $end
$var wire 1 * Ci $end
$var wire 1 . Co $end
$var wire 1 9 S $end
$upscope $end
$scope module cuatro $end
$var wire 1 : A $end
$var wire 1 ; B $end
$var wire 1 1 Co $end
$var wire 1 < S $end
$var wire 1 3 Ci $end
$upscope $end
$scope module dos $end
$var wire 1 = A $end
$var wire 1 > B $end
$var wire 1 4 Co $end
$var wire 1 ? S $end
$var wire 1 5 Ci $end
$upscope $end
$scope module ocho $end
$var wire 1 @ A $end
$var wire 1 A B $end
$var wire 1 + Co $end
$var wire 1 B S $end
$var wire 1 , Ci $end
$upscope $end
$scope module seis $end
$var wire 1 C A $end
$var wire 1 D B $end
$var wire 1 . Ci $end
$var wire 1 - Co $end
$var wire 1 E S $end
$upscope $end
$scope module siete $end
$var wire 1 F A $end
$var wire 1 G B $end
$var wire 1 - Ci $end
$var wire 1 , Co $end
$var wire 1 H S $end
$upscope $end
$scope module tres $end
$var wire 1 I A $end
$var wire 1 J B $end
$var wire 1 4 Ci $end
$var wire 1 3 Co $end
$var wire 1 K S $end
$upscope $end
$scope module uno $end
$var wire 1 L A $end
$var wire 1 M B $end
$var wire 1 % Ci $end
$var wire 1 5 Co $end
$var wire 1 N S $end
$upscope $end
$upscope $end
$upscope $end
$enddefinitions $end
#0
$dumpvars
0N
0M
0L
0K
0J
0I
0H
0G
0F
0E
0D
0C
0B
0A
0@
0?
0>
0=
0<
0;
0:
09
08
07
b0 6
05
04
03
b0 2
01
b0 0
b0 /
0.
0-
0,
0+
0*
b0 )
b0 (
b0 '
b0 &
0%
b0 $
b0 #
0"
b0 !
$end
#5000
b1 !
b1 6
19
17
b1 /
b1 0
1N
1M
b1 2
b1 $
b1 )
b1 '
#10000
09
b10 !
b10 6
1E
07
1C
b10 /
0N
b10 0
1?
0M
1>
b10 2
b10 $
b10 )
b10 '
#15000
b11 !
b11 6
19
17
b11 /
b11 0
1N
1M
b11 2
b11 $
b11 )
b11 '
#20000
09
0E
b100 !
b100 6
1H
07
0C
1F
b100 /
0N
0?
b100 0
1K
0M
0>
1J
b100 2
b100 $
b100 )
b100 '
#25000
b101 !
b101 6
19
17
b101 /
b101 0
1N
1M
b101 2
b101 $
b101 )
b101 '
#30000
09
b110 !
b110 6
1E
07
1C
b110 /
0N
b110 0
1?
0M
1>
b110 2
b110 $
b110 )
b110 '
#35000
b111 !
b111 6
19
17
b111 /
b111 0
1N
1M
b111 2
b111 $
b111 )
b111 '
#40000
09
0E
0H
b1000 !
b1000 6
1B
07
0C
0F
1@
b1000 /
0N
0?
0K
b1000 0
1<
0M
0>
0J
1;
b1000 2
b1000 $
b1000 )
b1000 '
#45000
b1001 !
b1001 6
19
17
b1001 /
b1001 0
1N
1M
b1001 2
b1001 $
b1001 )
b1001 '
#50000
09
b1010 !
b1010 6
1E
07
1C
b1010 /
0N
b1010 0
1?
0M
1>
b1010 2
b1010 $
b1010 )
b1010 '
#55000
b1011 !
b1011 6
19
17
b1011 /
b1011 0
1N
1M
b1011 2
b1011 $
b1011 )
b1011 '
#60000
09
0E
b1100 !
b1100 6
1H
07
0C
1F
b1100 /
0N
0?
b1100 0
1K
0M
0>
1J
b1100 2
b1100 $
b1100 )
b1100 '
#65000
b1101 !
b1101 6
19
17
b1101 /
b1101 0
1N
1M
b1101 2
b1101 $
b1101 )
b1101 '
#70000
09
b1110 !
b1110 6
1E
07
1C
b1110 /
0N
b1110 0
1?
0M
1>
b1110 2
b1110 $
b1110 )
b1110 '
#75000
b1111 !
b1111 6
19
17
b1111 /
b1111 0
1N
1M
b1111 2
b1111 $
b1111 )
b1111 '
#80000
0H
0F
0B
0E
0@
b1 !
b1 6
19
0K
0C
17
0<
b1 /
04
0?
0M
0>
0J
0;
b1 0
1N
05
b0 2
1L
b0 $
b0 )
b1 #
b1 (
b1 &
b0 '
#85000
1E
b10 !
b10 6
09
1C
07
b10 /
1?
b10 0
0N
15
1M
b1 2
b1 $
b1 )
b1 '
#90000
0H
19
b11 !
b11 6
1E
0F
17
1C
b11 /
0K
04
1N
05
b11 0
1?
0M
1>
b10 2
b10 $
b10 )
b10 '
#95000
1H
1F
0E
b100 !
b100 6
09
0C
07
1K
b100 /
14
0?
b100 0
0N
15
1M
b11 2
b11 $
b11 )
b11 '
#100000
0B
19
0E
b101 !
b101 6
1H
0@
17
0C
1F
b101 /
0<
04
03
1N
05
0?
b101 0
1K
0M
0>
1J
b100 2
b100 $
b100 )
b100 '
#105000
1E
b110 !
b110 6
09
1C
07
b110 /
1?
b110 0
0N
15
1M
b101 2
b101 $
b101 )
b101 '
#110000
0B
1H
0@
19
b111 !
b111 6
1E
1F
0<
17
1C
03
b111 /
1K
04
1N
05
b111 0
1?
0M
1>
b110 2
b110 $
b110 )
b110 '
#115000
1B
0H
1@
0F
0E
b1000 !
b1000 6
09
1<
13
0C
07
0K
b1000 /
14
0?
b1000 0
0N
15
1M
b111 2
b111 $
b111 )
b111 '
#120000
19
0E
0H
b1001 !
b1001 6
1B
17
0C
0F
1@
b1001 /
04
03
0"
01
1N
05
0?
0K
b1001 0
1<
0M
0>
0J
1;
b1000 2
b1000 $
b1000 )
b1000 '
#125000
1E
b1010 !
b1010 6
09
1C
07
b1010 /
1?
b1010 0
0N
15
1M
b1001 2
b1001 $
b1001 )
b1001 '
#130000
0H
19
b1011 !
b1011 6
1E
0F
17
1C
b1011 /
0K
04
1N
05
b1011 0
1?
0M
1>
b1010 2
b1010 $
b1010 )
b1010 '
#135000
1H
1F
0E
b1100 !
b1100 6
09
0C
07
1K
b1100 /
14
0?
b1100 0
0N
15
1M
b1011 2
b1011 $
b1011 )
b1011 '
#140000
1B
19
0E
b1101 !
b1101 6
1H
1@
17
0C
1F
0"
01
b1101 /
1<
04
03
1N
05
0?
b1101 0
1K
0M
0>
1J
b1100 2
b1100 $
b1100 )
b1100 '
#145000
1E
b1110 !
b1110 6
09
1C
07
b1110 /
1?
b1110 0
0N
15
1M
b1101 2
b1101 $
b1101 )
b1101 '
#150000
1B
1H
1@
19
b1111 !
b1111 6
1E
1F
0"
01
1<
17
1C
03
b1111 /
1K
04
1N
05
b1111 0
1?
0M
1>
b1110 2
b1110 $
b1110 )
b1110 '
#155000
0B
0H
0@
0F
1"
11
0E
b0 !
b0 6
09
0<
13
0C
07
0K
b0 /
14
0?
b0 0
0N
15
1M
b1111 2
b1111 $
b1111 )
b1111 '
#160000
0H
0B
0F
0@
09
b10 !
b10 6
1E
03
0"
01
07
1C
04
0K
0<
b10 /
0M
0>
0J
0;
0N
05
b10 0
1?
b0 2
0L
1=
b0 $
b0 )
b10 #
b10 (
b10 &
b0 '
#165000
b11 !
b11 6
19
17
b11 /
b11 0
1N
1M
b1 2
b1 $
b1 )
b1 '
#170000
1H
09
b100 !
b100 6
0E
1F
07
0C
b100 /
1K
0N
b100 0
0?
14
0M
1>
b10 2
b10 $
b10 )
b10 '
#175000
b101 !
b101 6
19
17
b101 /
b101 0
1N
1M
b11 2
b11 $
b11 )
b11 '
#180000
0B
09
1E
b110 !
b110 6
1H
0@
07
1C
1F
b110 /
0<
03
0N
1?
04
b110 0
1K
0M
0>
1J
b100 2
b100 $
b100 )
b100 '
#185000
b111 !
b111 6
19
17
b111 /
b111 0
1N
1M
b101 2
b101 $
b101 )
b101 '
#190000
1B
0H
1@
09
b1000 !
b1000 6
0E
0F
07
0C
1<
b1000 /
13
0K
0N
b1000 0
0?
14
0M
1>
b110 2
b110 $
b110 )
b110 '
#195000
b1001 !
b1001 6
19
17
b1001 /
b1001 0
1N
1M
b111 2
b111 $
b111 )
b111 '
#200000
09
1E
0H
b1010 !
b1010 6
1B
07
1C
0F
1@
b1010 /
03
0"
01
0N
1?
04
0K
b1010 0
1<
0M
0>
0J
1;
b1000 2
b1000 $
b1000 )
b1000 '
#205000
b1011 !
b1011 6
19
17
b1011 /
b1011 0
1N
1M
b1001 2
b1001 $
b1001 )
b1001 '
#210000
1H
09
b1100 !
b1100 6
0E
1F
07
0C
b1100 /
1K
0N
b1100 0
0?
14
0M
1>
b1010 2
b1010 $
b1010 )
b1010 '
#215000
b1101 !
b1101 6
19
17
b1101 /
b1101 0
1N
1M
b1011 2
b1011 $
b1011 )
b1011 '
#220000
1B
09
1E
b1110 !
b1110 6
1H
1@
07
1C
1F
0"
01
b1110 /
1<
03
0N
1?
04
b1110 0
1K
0M
0>
1J
b1100 2
b1100 $
b1100 )
b1100 '
#225000
b1111 !
b1111 6
19
17
b1111 /
b1111 0
1N
1M
b1101 2
b1101 $
b1101 )
b1101 '
#230000
0B
0H
0@
09
b0 !
b0 6
0E
0F
1"
11
07
0C
0<
b0 /
13
0K
0N
b0 0
0?
14
0M
1>
b1110 2
b1110 $
b1110 )
b1110 '
#235000
b1 !
b1 6
19
17
b1 /
b1 0
1N
1M
b1111 2
b1111 $
b1111 )
b1111 '
#240000
0H
0B
1E
0F
0@
b11 !
b11 6
19
1C
03
0"
01
17
04
0K
0<
b11 /
1?
0M
0>
0J
0;
b11 0
1N
05
b0 2
1L
b0 $
b0 )
b11 #
b11 (
b11 &
b0 '
#245000
1H
1F
0E
b100 !
b100 6
09
0C
07
1K
b100 /
14
0?
b100 0
0N
15
1M
b1 2
b1 $
b1 )
b1 '
#250000
19
b101 !
b101 6
0E
17
0C
b101 /
1N
05
b101 0
0?
0M
1>
b10 2
b10 $
b10 )
b10 '
#255000
1E
b110 !
b110 6
09
1C
07
b110 /
1?
b110 0
0N
15
1M
b11 2
b11 $
b11 )
b11 '
#260000
0B
19
1E
b111 !
b111 6
1H
0@
17
1C
1F
b111 /
0<
03
1N
05
1?
04
b111 0
1K
0M
0>
1J
b100 2
b100 $
b100 )
b100 '
#265000
1B
0H
1@
0F
0E
b1000 !
b1000 6
09
1<
13
0C
07
0K
b1000 /
14
0?
b1000 0
0N
15
1M
b101 2
b101 $
b101 )
b101 '
#270000
19
b1001 !
b1001 6
0E
17
0C
b1001 /
1N
05
b1001 0
0?
0M
1>
b110 2
b110 $
b110 )
b110 '
#275000
1E
b1010 !
b1010 6
09
1C
07
b1010 /
1?
b1010 0
0N
15
1M
b111 2
b111 $
b111 )
b111 '
#280000
19
1E
0H
b1011 !
b1011 6
1B
17
1C
0F
1@
b1011 /
03
0"
01
1N
05
1?
04
0K
b1011 0
1<
0M
0>
0J
1;
b1000 2
b1000 $
b1000 )
b1000 '
#285000
1H
1F
0E
b1100 !
b1100 6
09
0C
07
1K
b1100 /
14
0?
b1100 0
0N
15
1M
b1001 2
b1001 $
b1001 )
b1001 '
#290000
19
b1101 !
b1101 6
0E
17
0C
b1101 /
1N
05
b1101 0
0?
0M
1>
b1010 2
b1010 $
b1010 )
b1010 '
#295000
1E
b1110 !
b1110 6
09
1C
07
b1110 /
1?
b1110 0
0N
15
1M
b1011 2
b1011 $
b1011 )
b1011 '
#300000
1B
19
1E
b1111 !
b1111 6
1H
1@
17
1C
1F
0"
01
b1111 /
1<
03
1N
05
1?
04
b1111 0
1K
0M
0>
1J
b1100 2
b1100 $
b1100 )
b1100 '
#305000
0B
0H
0@
0F
1"
11
0E
b0 !
b0 6
09
0<
13
0C
07
0K
b0 /
14
0?
b0 0
0N
15
1M
b1101 2
b1101 $
b1101 )
b1101 '
#310000
19
b1 !
b1 6
0E
17
0C
b1 /
1N
05
b1 0
0?
0M
1>
b1110 2
b1110 $
b1110 )
b1110 '
#315000
1E
b10 !
b10 6
09
1C
07
b10 /
1?
b10 0
0N
15
1M
b1111 2
b1111 $
b1111 )
b1111 '
#320000
0B
0@
09
0E
b100 !
b100 6
1H
03
0"
01
07
0C
1F
0<
b100 /
0M
0>
0J
0;
0N
05
0?
04
b100 0
1K
b0 2
0L
0=
1I
b0 $
b0 )
b100 #
b100 (
b100 &
b0 '
#325000
b101 !
b101 6
19
17
b101 /
b101 0
1N
1M
b1 2
b1 $
b1 )
b1 '
#330000
09
b110 !
b110 6
1E
07
1C
b110 /
0N
b110 0
1?
0M
1>
b10 2
b10 $
b10 )
b10 '
#335000
b111 !
b111 6
19
17
b111 /
b111 0
1N
1M
b11 2
b11 $
b11 )
b11 '
#340000
1B
09
0E
b1000 !
b1000 6
0H
1@
07
0C
0F
b1000 /
1<
0N
0?
b1000 0
0K
13
0M
0>
1J
b100 2
b100 $
b100 )
b100 '
#345000
b1001 !
b1001 6
19
17
b1001 /
b1001 0
1N
1M
b101 2
b101 $
b101 )
b101 '
#350000
09
b1010 !
b1010 6
1E
07
1C
b1010 /
0N
b1010 0
1?
0M
1>
b110 2
b110 $
b110 )
b110 '
#355000
b1011 !
b1011 6
19
17
b1011 /
b1011 0
1N
1M
b111 2
b111 $
b111 )
b111 '
#360000
09
0E
1H
b1100 !
b1100 6
1B
07
0C
1F
1@
b1100 /
0"
01
0N
0?
1K
03
b1100 0
1<
0M
0>
0J
1;
b1000 2
b1000 $
b1000 )
b1000 '
#365000
b1101 !
b1101 6
19
17
b1101 /
b1101 0
1N
1M
b1001 2
b1001 $
b1001 )
b1001 '
#370000
09
b1110 !
b1110 6
1E
07
1C
b1110 /
0N
b1110 0
1?
0M
1>
b1010 2
b1010 $
b1010 )
b1010 '
#375000
b1111 !
b1111 6
19
17
b1111 /
b1111 0
1N
1M
b1011 2
b1011 $
b1011 )
b1011 '
#380000
0B
09
0E
b0 !
b0 6
0H
0@
07
0C
0F
b0 /
1"
11
0<
0N
0?
b0 0
0K
13
0M
0>
1J
b1100 2
b1100 $
b1100 )
b1100 '
#385000
b1 !
b1 6
19
17
b1 /
b1 0
1N
1M
b1101 2
b1101 $
b1101 )
b1101 '
#390000
09
b10 !
b10 6
1E
07
1C
b10 /
0N
b10 0
1?
0M
1>
b1110 2
b1110 $
b1110 )
b1110 '
#395000
b11 !
b11 6
19
17
b11 /
b11 0
1N
1M
b1111 2
b1111 $
b1111 )
b1111 '
#400000
1H
1F
0B
0E
0@
b101 !
b101 6
19
1K
0C
0"
01
17
03
0<
b101 /
04
0?
0M
0>
0J
0;
b101 0
1N
05
b0 2
1L
b0 $
b0 )
b101 #
b101 (
b101 &
b0 '
#405000
1E
b110 !
b110 6
09
1C
07
b110 /
1?
b110 0
0N
15
1M
b1 2
b1 $
b1 )
b1 '
#410000
0B
1H
0@
19
b111 !
b111 6
1E
1F
0<
17
1C
03
b111 /
1K
04
1N
05
b111 0
1?
0M
1>
b10 2
b10 $
b10 )
b10 '
#415000
1B
0H
1@
0F
0E
b1000 !
b1000 6
09
1<
13
0C
07
0K
b1000 /
14
0?
b1000 0
0N
15
1M
b11 2
b11 $
b11 )
b11 '
#420000
19
0E
b1001 !
b1001 6
0H
17
0C
0F
b1001 /
04
1N
05
0?
b1001 0
0K
0M
0>
1J
b100 2
b100 $
b100 )
b100 '
#425000
1E
b1010 !
b1010 6
09
1C
07
b1010 /
1?
b1010 0
0N
15
1M
b101 2
b101 $
b101 )
b101 '
#430000
0H
19
b1011 !
b1011 6
1E
0F
17
1C
b1011 /
0K
04
1N
05
b1011 0
1?
0M
1>
b110 2
b110 $
b110 )
b110 '
#435000
1H
1F
0E
b1100 !
b1100 6
09
0C
07
1K
b1100 /
14
0?
b1100 0
0N
15
1M
b111 2
b111 $
b111 )
b111 '
#440000
19
0E
1H
b1101 !
b1101 6
1B
17
0C
1F
1@
b1101 /
04
0"
01
1N
05
0?
1K
03
b1101 0
1<
0M
0>
0J
1;
b1000 2
b1000 $
b1000 )
b1000 '
#445000
1E
b1110 !
b1110 6
09
1C
07
b1110 /
1?
b1110 0
0N
15
1M
b1001 2
b1001 $
b1001 )
b1001 '
#450000
1B
1H
1@
19
b1111 !
b1111 6
1E
1F
0"
01
1<
17
1C
03
b1111 /
1K
04
1N
05
b1111 0
1?
0M
1>
b1010 2
b1010 $
b1010 )
b1010 '
#455000
0B
0H
0@
0F
1"
11
0E
b0 !
b0 6
09
0<
13
0C
07
0K
b0 /
14
0?
b0 0
0N
15
1M
b1011 2
b1011 $
b1011 )
b1011 '
#460000
19
0E
b1 !
b1 6
0H
17
0C
0F
b1 /
04
1N
05
0?
b1 0
0K
0M
0>
1J
b1100 2
b1100 $
b1100 )
b1100 '
#465000
1E
b10 !
b10 6
09
1C
07
b10 /
1?
b10 0
0N
15
1M
b1101 2
b1101 $
b1101 )
b1101 '
#470000
0H
19
b11 !
b11 6
1E
0F
17
1C
b11 /
0K
04
1N
05
b11 0
1?
0M
1>
b1110 2
b1110 $
b1110 )
b1110 '
#475000
1H
1F
0E
b100 !
b100 6
09
0C
07
1K
b100 /
14
0?
b100 0
0N
15
1M
b1111 2
b1111 $
b1111 )
b1111 '
#480000
1H
0B
1F
0@
09
b110 !
b110 6
1E
0"
01
07
1C
04
1K
03
0<
b110 /
0M
0>
0J
0;
0N
05
b110 0
1?
b0 2
0L
1=
b0 $
b0 )
b110 #
b110 (
b110 &
b0 '
#485000
b111 !
b111 6
19
17
b111 /
b111 0
1N
1M
b1 2
b1 $
b1 )
b1 '
#490000
1B
0H
1@
09
b1000 !
b1000 6
0E
0F
07
0C
1<
b1000 /
13
0K
0N
b1000 0
0?
14
0M
1>
b10 2
b10 $
b10 )
b10 '
#495000
b1001 !
b1001 6
19
17
b1001 /
b1001 0
1N
1M
b11 2
b11 $
b11 )
b11 '
#500000
09
1E
b1010 !
b1010 6
0H
07
1C
0F
b1010 /
0N
1?
04
b1010 0
0K
0M
0>
1J
b100 2
b100 $
b100 )
b100 '
#505000
b1011 !
b1011 6
19
17
b1011 /
b1011 0
1N
1M
b101 2
b101 $
b101 )
b101 '
#510000
1H
09
b1100 !
b1100 6
0E
1F
07
0C
b1100 /
1K
0N
b1100 0
0?
14
0M
1>
b110 2
b110 $
b110 )
b110 '
#515000
b1101 !
b1101 6
19
17
b1101 /
b1101 0
1N
1M
b111 2
b111 $
b111 )
b111 '
#520000
09
1E
1H
b1110 !
b1110 6
1B
07
1C
1F
1@
b1110 /
0"
01
0N
1?
04
1K
03
b1110 0
1<
0M
0>
0J
1;
b1000 2
b1000 $
b1000 )
b1000 '
#525000
b1111 !
b1111 6
19
17
b1111 /
b1111 0
1N
1M
b1001 2
b1001 $
b1001 )
b1001 '
#530000
0B
0H
0@
09
b0 !
b0 6
0E
0F
1"
11
07
0C
0<
b0 /
13
0K
0N
b0 0
0?
14
0M
1>
b1010 2
b1010 $
b1010 )
b1010 '
#535000
b1 !
b1 6
19
17
b1 /
b1 0
1N
1M
b1011 2
b1011 $
b1011 )
b1011 '
#540000
09
1E
b10 !
b10 6
0H
07
1C
0F
b10 /
0N
1?
04
b10 0
0K
0M
0>
1J
b1100 2
b1100 $
b1100 )
b1100 '
#545000
b11 !
b11 6
19
17
b11 /
b11 0
1N
1M
b1101 2
b1101 $
b1101 )
b1101 '
#550000
1H
09
b100 !
b100 6
0E
1F
07
0C
b100 /
1K
0N
b100 0
0?
14
0M
1>
b1110 2
b1110 $
b1110 )
b1110 '
#555000
b101 !
b101 6
19
17
b101 /
b101 0
1N
1M
b1111 2
b1111 $
b1111 )
b1111 '
#560000
1H
0B
1E
1F
0@
b111 !
b111 6
19
1C
0"
01
17
04
1K
03
0<
b111 /
1?
0M
0>
0J
0;
b111 0
1N
05
b0 2
1L
b0 $
b0 )
b111 #
b111 (
b111 &
b0 '
#565000
1B
0H
1@
0F
0E
b1000 !
b1000 6
09
1<
13
0C
07
0K
b1000 /
14
0?
b1000 0
0N
15
1M
b1 2
b1 $
b1 )
b1 '
#570000
19
b1001 !
b1001 6
0E
17
0C
b1001 /
1N
05
b1001 0
0?
0M
1>
b10 2
b10 $
b10 )
b10 '
#575000
1E
b1010 !
b1010 6
09
1C
07
b1010 /
1?
b1010 0
0N
15
1M
b11 2
b11 $
b11 )
b11 '
#580000
19
1E
b1011 !
b1011 6
0H
17
1C
0F
b1011 /
1N
05
1?
04
b1011 0
0K
0M
0>
1J
b100 2
b100 $
b100 )
b100 '
#585000
1H
1F
0E
b1100 !
b1100 6
09
0C
07
1K
b1100 /
14
0?
b1100 0
0N
15
1M
b101 2
b101 $
b101 )
b101 '
#590000
19
b1101 !
b1101 6
0E
17
0C
b1101 /
1N
05
b1101 0
0?
0M
1>
b110 2
b110 $
b110 )
b110 '
#595000
1E
b1110 !
b1110 6
09
1C
07
b1110 /
1?
b1110 0
0N
15
1M
b111 2
b111 $
b111 )
b111 '
#600000
19
1E
1H
b1111 !
b1111 6
1B
17
1C
1F
1@
b1111 /
0"
01
1N
05
1?
04
1K
03
b1111 0
1<
0M
0>
0J
1;
b1000 2
b1000 $
b1000 )
b1000 '
#605000
0B
0H
0@
0F
1"
11
0E
b0 !
b0 6
09
0<
13
0C
07
0K
b0 /
14
0?
b0 0
0N
15
1M
b1001 2
b1001 $
b1001 )
b1001 '
#610000
19
b1 !
b1 6
0E
17
0C
b1 /
1N
05
b1 0
0?
0M
1>
b1010 2
b1010 $
b1010 )
b1010 '
#615000
1E
b10 !
b10 6
09
1C
07
b10 /
1?
b10 0
0N
15
1M
b1011 2
b1011 $
b1011 )
b1011 '
#620000
19
1E
b11 !
b11 6
0H
17
1C
0F
b11 /
1N
05
1?
04
b11 0
0K
0M
0>
1J
b1100 2
b1100 $
b1100 )
b1100 '
#625000
1H
1F
0E
b100 !
b100 6
09
0C
07
1K
b100 /
14
0?
b100 0
0N
15
1M
b1101 2
b1101 $
b1101 )
b1101 '
#630000
19
b101 !
b101 6
0E
17
0C
b101 /
1N
05
b101 0
0?
0M
1>
b1110 2
b1110 $
b1110 )
b1110 '
#635000
1E
b110 !
b110 6
09
1C
07
b110 /
1?
b110 0
0N
15
1M
b1111 2
b1111 $
b1111 )
b1111 '
#640000
09
0E
0H
b1000 !
b1000 6
1B
0"
01
07
0C
0F
1@
b1000 /
0M
0>
0J
0;
0N
05
0?
04
0K
03
b1000 0
1<
b0 2
0L
0=
0I
1:
b0 $
b0 )
b1000 #
b1000 (
b1000 &
b0 '
#645000
b1001 !
b1001 6
19
17
b1001 /
b1001 0
1N
1M
b1 2
b1 $
b1 )
b1 '
#650000
09
b1010 !
b1010 6
1E
07
1C
b1010 /
0N
b1010 0
1?
0M
1>
b10 2
b10 $
b10 )
b10 '
#655000
b1011 !
b1011 6
19
17
b1011 /
b1011 0
1N
1M
b11 2
b11 $
b11 )
b11 '
#660000
09
0E
b1100 !
b1100 6
1H
07
0C
1F
b1100 /
0N
0?
b1100 0
1K
0M
0>
1J
b100 2
b100 $
b100 )
b100 '
#665000
b1101 !
b1101 6
19
17
b1101 /
b1101 0
1N
1M
b101 2
b101 $
b101 )
b101 '
#670000
09
b1110 !
b1110 6
1E
07
1C
b1110 /
0N
b1110 0
1?
0M
1>
b110 2
b110 $
b110 )
b110 '
#675000
b1111 !
b1111 6
19
17
b1111 /
b1111 0
1N
1M
b111 2
b111 $
b111 )
b111 '
#680000
09
0E
0H
b0 !
b0 6
0B
07
0C
0F
0@
b0 /
0N
0?
0K
b0 0
0<
1"
11
0M
0>
0J
1;
b1000 2
b1000 $
b1000 )
b1000 '
#685000
b1 !
b1 6
19
17
b1 /
b1 0
1N
1M
b1001 2
b1001 $
b1001 )
b1001 '
#690000
09
b10 !
b10 6
1E
07
1C
b10 /
0N
b10 0
1?
0M
1>
b1010 2
b1010 $
b1010 )
b1010 '
#695000
b11 !
b11 6
19
17
b11 /
b11 0
1N
1M
b1011 2
b1011 $
b1011 )
b1011 '
#700000
09
0E
b100 !
b100 6
1H
07
0C
1F
b100 /
0N
0?
b100 0
1K
0M
0>
1J
b1100 2
b1100 $
b1100 )
b1100 '
#705000
b101 !
b101 6
19
17
b101 /
b101 0
1N
1M
b1101 2
b1101 $
b1101 )
b1101 '
